MANIFEST.in
setup.cfg
setup.py
stratus_api/sql/__init__.py
stratus_api/sql/db.py
stratus_api/sql/migrations.py
stratus_api/sql/models.py
stratus_api_sql.egg-info/PKG-INFO
stratus_api_sql.egg-info/SOURCES.txt
stratus_api_sql.egg-info/dependency_links.txt
stratus_api_sql.egg-info/requires.txt
stratus_api_sql.egg-info/top_level.txt