Metadata-Version: 2.1
Name: stratus-api-sql
Version: 0.0.4
Summary: Simplified SQL API
Home-page: https://bitbucket.org/adarainc/stratus-api-sql
Author: DOT
Author-email: dot@adara.com
Classifier: Programming Language :: Python :: 3
Classifier: License :: OSI Approved :: MIT License
Classifier: Operating System :: OS Independent
Requires-Python: >=3.11
